LICENSE
README.md
thorbanks/__init__.py
thorbanks/abstract_models.py
thorbanks/apps.py
thorbanks/checks.py
thorbanks/forms.py
thorbanks/loading.py
thorbanks/settings.py
thorbanks/signals.py
thorbanks/static/img/payment/amex.png
thorbanks/static/img/payment/danske.png
thorbanks/static/img/payment/discover.png
thorbanks/static/img/payment/lhv.png
thorbanks/static/img/payment/mastercard.png
thorbanks/static/img/payment/nordea.png
thorbanks/static/img/payment/paypal.png
thorbanks/static/img/payment/seb.png
thorbanks/static/img/payment/swedbank.png
thorbanks/static/img/payment/visa.png
thorbanks/templates/thorbanks/auth-request.html
thorbanks/templates/thorbanks/input_option.html
thorbanks/templates/thorbanks/payment-request.html
thorbanks/templates/thorbanks/payment_widget.html
thorbanks/templates/thorbanks/test_response.html
thorbanks/urls.py
thorbanks/utils.py
thorbanks/views.py
thorbanks_models/__init__.py
thorbanks_models/admin.py
thorbanks_models/apps.py
thorbanks_models/models.py
django_thorbanks-0.7.2.dist-info/LICENSE
django_thorbanks-0.7.2.dist-info/METADATA
django_thorbanks-0.7.2.dist-info/WHEEL
django_thorbanks-0.7.2.dist-info/RECORD
