Metadata-Version: 2.1
Name: django-thorbanks
Version: 0.7.2
Summary: `django-thorbanks` provides a Django application for Estonian banklinks (iPizza protocol).
Home-page: http://thorgate.eu
License: BSD-3-Clause
Author: Thorgate
Author-email: info@thorgate.eu
Requires-Python: >=3.7,<4.0
Classifier: Development Status :: 4 - Beta
Classifier: Environment :: Web Environment
Classifier: Framework :: Django
Classifier: Intended Audience :: Developers
Classifier: License :: OSI Approved :: BSD License
Classifier: Operating System :: OS Independent
Classifier: Programming Language :: Python
Classifier: Programming Language :: Python :: 3
Classifier: Programming Language :: Python :: 3.7
Classifier: Programming Language :: Python :: 3.8
Classifier: Programming Language :: Python :: 3.9
Classifier: Programming Language :: Python :: 3.10
Classifier: Programming Language :: Python :: 3.11
Requires-Dist: Django (>=1.11.27)
Requires-Dist: cryptography (>=2)
Project-URL: Repository, https://github.com/thorgate/django-thorbanks
